{
  "version": "5.3.0a0",
  "flags": {},
  "shapes": [
    {
      "label": "liqing_kengcao",
      "points": [
        [
          2012.3076923076922,
          1193.5384615384617
        ],
        [
          2073.846153846154,
          1219.6923076923078
        ],
        [
          2126.153846153846,
          1208.9230769230771
        ],
        [
          2107.6923076923076,
          1195.076923076923
        ],
        [
          2070.7692307692305,
          1182.769230769231
        ],
        [
          2021.5384615384614,
          1181.2307692307693
        ]
      ],
      "group_id": null,
      "description": "",
      "shape_type": "polygon",
      "flags": {}
    },
    {
      "label": "liqing_kengcao",
      "points": [
        [
          2283.076923076923,
          1281.2307692307693
        ],
        [
          2320.0,
          1281.2307692307693
        ],
        [
          2349.230769230769,
          1282.769230769231
        ],
        [
          2366.153846153846,
          1270.4615384615386
        ],
        [
          2343.076923076923,
          1258.1538461538462
        ],
        [
          2316.9230769230767,
          1258.1538461538462
        ]
      ],
      "group_id": null,
      "description": "",
      "shape_type": "polygon",
      "flags": {}
    },
    {
      "label": "liqing_kengcao",
      "points": [
        [
          897.1153846153845,
          1366.2307692307693
        ],
        [
          918.2692307692307,
          1365.2692307692307
        ],
        [
          950.0,
          1358.5384615384617
        ],
        [
          977.8846153846154,
          1348.923076923077
        ],
        [
          979.8076923076923,
          1335.4615384615386
        ],
        [
          950.0,
          1326.8076923076924
        ],
        [
          932.6923076923076,
          1326.8076923076924
        ],
        [
          904.8076923076923,
          1344.1153846153848
        ]
      ],
      "group_id": null,
      "description": "",
      "shape_type": "polygon",
      "flags": {}
    }
  ],
  "imagePath": "avt_2024_12_24___14_17_35_620_2165.jpg",
  "imageData": null,
  "imageHeight": 2544,
  "imageWidth": 4080
}